{
  "snippets": [
    {
      "title": "First snippet heeader",
      "content": "Content",
      "description": "This is description of first snippet. And I wrote it now checking if patch or put. Hahahaha. dfhfghdfghfgjfgjfgjfjfgjhdg",
      "id": 1
    },
    {
      "id": 2,
      "title": "Second snippet header",
      "content": "Second snippet content - checl how to parse code into json format",
      "description": "This is description of second snippet",
      "tags": [
        "angular",
        "typescript"
      ],
      "links": []
    }
  ]
}